ceasar/__init__.py
ceasar/cli.py
ceasar/main.py
ceasar_toolkit-1.1.0.dist-info/licenses/LICENSE
ceasar_toolkit-1.1.0.dist-info/METADATA
ceasar_toolkit-1.1.0.dist-info/WHEEL
ceasar_toolkit-1.1.0.dist-info/entry_points.txt
ceasar_toolkit-1.1.0.dist-info/top_level.txt
ceasar_toolkit-1.1.0.dist-info/RECORD
