Metadata-Version: 2.4
Name: ceasar-toolkit
Version: 1.1.0
Summary: Caesar Cipher CLI Toolkit for encryption, PDF, and folder protection
Author: Hounaar
License: MIT
Classifier: Programming Language :: Python :: 3
Classifier: License :: OSI Approved :: MIT License
Requires-Python: >=3.8
License-File: LICENSE
Requires-Dist: colorama
Requires-Dist: PyPDF2
Dynamic: author
Dynamic: classifier
Dynamic: description
Dynamic: description-content-type
Dynamic: license
Dynamic: license-file
Dynamic: requires-dist
Dynamic: requires-python
Dynamic: summary
